pyfastnoiselite.libs/libstdc++-0d31ccbe.so.6.0.32
pyfastnoiselite.libs/libgcc_s-a0b57c20.so.1
pyfastnoiselite-0.0.7.dist-info/WHEEL
pyfastnoiselite-0.0.7.dist-info/top_level.txt
pyfastnoiselite-0.0.7.dist-info/METADATA
pyfastnoiselite-0.0.7.dist-info/RECORD
pyfastnoiselite-0.0.7.dist-info/licenses/LICENSE
pyfastnoiselite/pyfastnoiselite.cpython-310-x86_64-linux-gnu.so
pyfastnoiselite/__init__.py
