Metadata-Version: 2.1
Name: pyfastnoiselite
Version: 0.0.7
Summary: Cython wrapper for Auburns' FastNoise Lite.
Home-page: https://github.com/tizilogic/pyfastnoiselite
Author: Tiziano Bettio
Author-email: tc@tizilogic.com
Classifier: Programming Language :: Python :: 3
Classifier: License :: OSI Approved :: MIT License
Classifier: Operating System :: OS Independent
Requires-Python: >=3.6
License-File: LICENSE
Requires-Dist: numpy
